qstring-1.0.1.dist-info/METADATA
qstring-1.0.1.dist-info/WHEEL
qstring-1.0.1.dist-info/licenses/LICENSE
qstring/__init__.py
qstring/exc.py
qstring/nest.py
qstring/py.typed
qstring/unnest.py
qstring-1.0.1.dist-info/RECORD
