Metadata-Version: 2.1
Name: qstring
Version: 1.0.1
Summary: Parse querystring parameters to nested objects
Author-Email: Janne Vanhala <janne@fastmonkeys.com>
License: The MIT License (MIT)
Classifier: Development Status :: 5 - Production/Stable
Classifier: Intended Audience :: Developers
Classifier: License :: OSI Approved :: MIT License
Classifier: Operating System :: OS Independent
Classifier: Programming Language :: Python
Classifier: Programming Language :: Python :: 3
Classifier: Programming Language :: Python :: 3.8
Classifier: Programming Language :: Python :: 3.9
Classifier: Programming Language :: Python :: 3.10
Classifier: Programming Language :: Python :: 3.11
Classifier: Programming Language :: Python :: 3.12
Classifier: Programming Language :: Python :: Implementation :: CPython
Classifier: Programming Language :: Python :: Implementation :: PyPy
Classifier: Topic :: Software Development :: Libraries :: Python Modules
Project-URL: Documentation, http://qstring.readthedocs.org
Project-URL: Bug tracker, http://github.com/fastmonkeys/qstring/issues
Project-URL: Code, http://github.com/fastmonkeys/qstring
Requires-Python: >=3.8
